README.md
setup.py
user_tweet_downloader/__init__.py
user_tweet_downloader/accounts.py
user_tweet_downloader/constants.py
user_tweet_downloader/jsons_toxlsx.py
user_tweet_downloader/main.py
user_tweet_downloader/tweet_download.py
user_tweet_downloader.egg-info/PKG-INFO
user_tweet_downloader.egg-info/SOURCES.txt
user_tweet_downloader.egg-info/dependency_links.txt
user_tweet_downloader.egg-info/requires.txt
user_tweet_downloader.egg-info/top_level.txt