Metadata-Version: 1.1
Name: user-tweet-downloader
Version: 1.1.0
Summary: Download the 3.200 most recent tweets of any Twitter public account
Home-page: https://github.com/AdriaPadilla/user_tweet_downloader
Author: Adrian Padilla
Author-email: adrian.padilla.m@gmail.com
License: UNKNOWN
Platform: UNKNOWN
Classifier: Programming Language :: Python :: 3
Classifier: License :: OSI Approved :: MIT License
Classifier: Operating System :: OS Independent
